agentic_student_assistant/__init__.py
agentic_student_assistant/core/__init__.py
agentic_student_assistant/core/base/__init__.py
agentic_student_assistant/core/base/base_agent.py
agentic_student_assistant/core/base/fallback_agent.py
agentic_student_assistant/core/configs/__init__.py
agentic_student_assistant/core/configs/config.yaml
agentic_student_assistant/core/configs/agents/__init__.py
agentic_student_assistant/core/configs/agents/curriculum.yaml
agentic_student_assistant/core/configs/models/__init__.py
agentic_student_assistant/core/configs/models/gpt35.yaml
agentic_student_assistant/core/configs/models/gpt4.yaml
agentic_student_assistant/core/configs/prompts/__init__.py
agentic_student_assistant/core/configs/prompts/prompts.yaml
agentic_student_assistant/core/orchestration/__init__.py
agentic_student_assistant/core/orchestration/main_graph.py
agentic_student_assistant/core/orchestration/orchestrator_agent.py
agentic_student_assistant/core/orchestration/router_agent.py
agentic_student_assistant/core/tests/verify_cache_stats.py
agentic_student_assistant/core/utils/__init__.py
agentic_student_assistant/core/utils/cache.py
agentic_student_assistant/core/utils/chunker.py
agentic_student_assistant/core/utils/config_loader.py
agentic_student_assistant/core/utils/llm_factory.py
agentic_student_assistant/core/utils/logging_manager.py
agentic_student_assistant/core/utils/parse_pdf.py
agentic_student_assistant/core/utils/prompt_loader.py
agentic_student_assistant/core/utils/sheets_logger.py
agentic_student_assistant/core/utils/upload_parser.py
agentic_student_assistant/talk2books/__init__.py
agentic_student_assistant/talk2books/agents/__init__.py
agentic_student_assistant/talk2books/agents/books_recommend_agent.py
agentic_student_assistant/talk2books/configs/prompts.yaml
agentic_student_assistant/talk2books/tools/__init__.py
agentic_student_assistant/talk2books/tools/book_utils.py
agentic_student_assistant/talk2books/tools/googlebooks_tool.py
agentic_student_assistant-0.1.2.dist-info/METADATA
agentic_student_assistant-0.1.2.dist-info/WHEEL
agentic_student_assistant-0.1.2.dist-info/RECORD
