Metadata-Version: 2.4
Name: agentic-student-assistant
Version: 0.1.2
Summary: A sophisticated student assistant using agentic AI.
Project-URL: Homepage, https://github.com/hsrak/Agentic_Student_Assistant
Project-URL: Bug Tracker, https://github.com/hsrak/Agentic_Student_Assistant/issues
Author-email: Rakesh <hsrakesh71@gmail.com>
License: MIT
Classifier: License :: OSI Approved :: MIT License
Classifier: Operating System :: OS Independent
Classifier: Programming Language :: Python :: 3
Requires-Python: >=3.10
Requires-Dist: chromadb>=0.4.24
Requires-Dist: faiss-cpu>=1.7.4
Requires-Dist: google-search-results==2.4.2
Requires-Dist: groq>=0.4.0
Requires-Dist: gspread
Requires-Dist: hydra-core>=1.3.0
Requires-Dist: ipython>=8.0.0
Requires-Dist: langchain-community==0.0.38
Requires-Dist: langchain-core==0.1.53
Requires-Dist: langchain==0.1.20
Requires-Dist: matplotlib
Requires-Dist: networkx
Requires-Dist: oauth2client
Requires-Dist: omegaconf>=2.3.0
Requires-Dist: openai==0.28.1
Requires-Dist: pandas
Requires-Dist: pdfplumber>=0.10.2
Requires-Dist: pydantic<2
Requires-Dist: pylint
Requires-Dist: pymupdf>=1.23.2
Requires-Dist: python-dotenv>=1.0.0
Requires-Dist: qdrant-client>=1.6.0
Requires-Dist: redis
Requires-Dist: requests>=2.31.0
Requires-Dist: rich>=13.7.0
Requires-Dist: seaborn
Requires-Dist: sentence-transformers>=2.2.0
Requires-Dist: setuptools
Requires-Dist: streamlit>=1.35.0
Requires-Dist: tabulate
Requires-Dist: tiktoken>=0.6.0
Requires-Dist: torch
Requires-Dist: twine
Requires-Dist: wheel
Requires-Dist: zstandard
